src/__init__.py
src/ming.py
src/cmd/__init__.py
src/cmd/cmd_manager.py
src/config/__init__.py
src/config/config_manager.py
src/config/global_config.py
src/config/peewee_config.py
src/config/server_config.py
src/local/__init__.py
src/local/http_server.py
src/local/net_manager.py
src/local/pc_info.py
src/local/pc_test.py
src/script/__init__.py
src/script/script_manager.py
src/script/script_store.py
src/server/__init__.py
src/server/server_config.py
src/server/server_store.py
src/utils/__init__.py
src/utils/convertUtils.py
src/utils/iputils.py
src/utils/timeUtils.py
jiuming_tools-2.34.dist-info/METADATA
jiuming_tools-2.34.dist-info/WHEEL
jiuming_tools-2.34.dist-info/entry_points.txt
jiuming_tools-2.34.dist-info/top_level.txt
jiuming_tools-2.34.dist-info/RECORD
