Metadata-Version: 2.1
Name: jiuming-tools
Version: 2.34
Summary: 个人常用功能
Home-page: https://github.com/xujiuming/jiuming-tools
Author: ming
License: MIT
Platform: linux
Requires-Dist: Click
Requires-Dist: psutil
Requires-Dist: PyYAML
Requires-Dist: gitpython
Requires-Dist: bcrypt
Requires-Dist: speedtest-cli
Requires-Dist: pexpect
Requires-Dist: scapy
Requires-Dist: lxml
Requires-Dist: requests-cache
Requires-Dist: peewee
Requires-Dist: prettytable
